cyclic_light.v
module cyclic_light (clk, light);
    parameter s0 = 2'b00, s1 = 2'b01, s2 = 2'b10;
    parameter RED=3'b100, GREEN = 3'b010, YELLOW = 3'b001;

    input clk; 
    output reg[2:0] light = RED;

    
    
    reg[1:0] state = s0;

    always @(posedge clk)
        case(state)

            s0: begin 
                light <= GREEN; state <= s1;
            end 
            s1: begin
                
                light <= YELLOW; state <= s2;
            end
            s2: begin
                light <= RED; state <= s0;
            end

            default: begin 

                light <= RED; state <= s0;
            end


        endcase 

endmodule

cyclic_tb.v
`timescale 1ns/1ns
`include "cyclic_light.v"

module cyclic_tb;

    reg clk = 0; 
    wire [2:0] light; 

    cyclic_light ins(clk, light);

    always begin

        #5
        clk = ~clk;

    end

    initial begin

        $dumpfile("cyclic.vcd");
        $dumpvars(0, cyclic_tb);

        $monitor ($time, " RGY: %b", light);

        #100;
        $finish;

    end

endmodule

cyclic.vcd
$date
	Fri Feb 28 12:21:03 2025
$end
$version
	Icarus Verilog
$end
$timescale
	1ns
$end
$scope module cyclic_tb $end
$var wire 3 ! light [2:0] $end
$var reg 1 " clk $end
$scope module ins $end
$var wire 1 " clk $end
$var reg 3 # light [2:0] $end
$var reg 2 $ state [1:0] $end
$upscope $end
$upscope $end
$enddefinitions $end
#0
$dumpvars
b0 $
b100 #
0"
b100 !
$end
#5
b1 $
b10 !
b10 #
1"
#10
0"
#15
b10 $
b1 !
b1 #
1"
#20
0"
#25
b0 $
b100 !
b100 #
1"
#30
0"
#35
b1 $
b10 !
b10 #
1"
#40
0"
#45
b10 $
b1 !
b1 #
1"
#50
0"
#55
b0 $
b100 !
b100 #
1"
#60
0"
#65
b1 $
b10 !
b10 #
1"
#70
0"
#75
b10 $
b1 !
b1 #
1"
#80
0"
#85
b0 $
b100 !
b100 #
1"
#90
0"
#95
b1 $
b10 !
b10 #
1"
