two_bit_comp.v
module two_bit_comp(A, B, Y);

    input [1:0] A, B;
    output Y;

    //assign Y = A > B;

    assign Y = (A[1] & ~B[1]) | (A[0] & ~B[0] & ~B[1]) | (A[0] & A[1] & ~B[0]);


endmodule

two_bit_comp_tb.v
`timescale 1ns/1ns
`include "two_bit_comp.v"

module two_bit_comp_tb;

    reg[1:0] A,B;
    wire Y;

    two_bit_comp ins1(A, B, Y);

    initial begin

        $dumpfile("two_bit_comp.vcd");
        $dumpvars(0, two_bit_comp_tb);

        {A, B} = 4'd0; #20;
        {A, B} = 4'd1; #20;
        {A, B} = 4'd2; #20;
        {A, B} = 4'd3; #20;
        {A, B} = 4'd4; #20;
        {A, B} = 4'd5; #20;
        {A, B} = 4'd6; #20;
        {A, B} = 4'd7; #20;
        {A, B} = 4'd8; #20;
        {A, B} = 4'd9; #20;
        {A, B} = 4'd10; #20;
        {A, B} = 4'd11; #20;
        {A, B} = 4'd12; #20;
        {A, B} = 4'd13; #20;
        {A, B} = 4'd14; #20;
        {A, B} = 4'd15; #20;
        $display("Test Run Successful");


    end

endmodule

two_bit_comp.vcd
$date
	Thu Feb 27 22:13:53 2025
$end
$version
	Icarus Verilog
$end
$timescale
	1ns
$end
$scope module two_bit_comp_tb $end
$var wire 1 ! Y $end
$var reg 2 " A [1:0] $end
$var reg 2 # B [1:0] $end
$scope module ins1 $end
$var wire 2 $ A [1:0] $end
$var wire 2 % B [1:0] $end
$var wire 1 ! Y $end
$upscope $end
$upscope $end
$enddefinitions $end
#0
$dumpvars
b0 %
b0 $
b0 #
b0 "
0!
$end
#20
b1 #
b1 %
#40
b10 #
b10 %
#60
b11 #
b11 %
#80
1!
b1 "
b1 $
b0 #
b0 %
#100
0!
b1 #
b1 %
#120
b10 #
b10 %
#140
b11 #
b11 %
#160
1!
b10 "
b10 $
b0 #
b0 %
#180
b1 #
b1 %
#200
0!
b10 #
b10 %
#220
b11 #
b11 %
#240
1!
b11 "
b11 $
b0 #
b0 %
#260
b1 #
b1 %
#280
b10 #
b10 %
#300
0!
b11 #
b11 %
